{"pDMKlB2uV8D0RtdmR5d1NQ==":"ai-g6116889b1-1920-1920x1076.jpeg","9SlS4Ru9Kjg5Ta2LoX/ZIw==":"logo-3-192x192.png","BD32Kr5Nd/gSKwHyAeYXkA==":"liliana-hernandez-portada-1054x1581.jpeg","gwYALERC1OFJR+uj30+Vxg==":"imagen%20de%20whatsapp%202023-02-26%20a%20las%2014.49.39%20f-921x1228.jpeg","uSiNlEM6+bE27lyLW8sGpA==":"herbolaria-921x651.png","83prbkLjqiBxP/m9GLXDAw==":"cacao-921x651.png","KEuBQCaC1ACPLPHtEFW+Kw==":"geometria-921x651.png","cxBDIrr010qocNNET/q03Q==":"devocion-921x651.png","vVPsEv8ZPlVfaesBbUt02g==":"conexion-921x651.png","44JTlnIsXKKOsiddiw1Rvg==":"cristales-921x651.png","vhXQREGuwiEtXWV7Q93TwA==":"circulo-921x651.png","dHXwuAHa/W/A751fqIiCRg==":"imagen%20de%20whatsapp%202023-02-26%20a%20las%2014.49.39%20f-921x1228.jpeg","JAU0Pmv09KgpZYJb6v2aLA==":"tambot-921x651.png","3eZYv8x1pK5nF1NZhmaQWA==":"inicio-1366x768.png","uU94NL2G6uNvE0d9CAvw3Q==":"imagen%20de%20whatsapp%202023-02-26%20a%20las%2014.50.51-1600x1200.jpeg","qtGyg0L+iwfgFeBNUbeM8A==":"imagen%20de%20whatsapp%202023-02-26%20a%20las%2014.50.51-1600x1200.jpeg","xsDa3xWVYXEc5JmTJVJJZQ==":"imagen%20de%20whatsapp%202023-02-26%20a%20las%2014.50.51-1600x1200.jpeg","W/mt8twyyehtWNYGYhe/ug==":"logos%20amigable%20vr_mesa%20de%20trabajo%201-399x399.png","aOK8DUKDiDeFkKoxxSmInw==":"logos%20finales_mesa%20de%20trabajo%201%20copia%203-1921x1921.png","P1ZMUvkfdW85B/rA7T8E8w==":"logo%202022%2002%20(2)-1000x1000.png","0MAmPxXp5a986KAzlZGUAg==":"escapa-1080x1080.png","kDBWr0Hu5uaQof/2IlHmVg==":"plantea-1600x1600.jpg","y9XT8qkeAKbKEemEZI8rGA==":"neem-4-399x399.png","GTb7prMewyT/3RlB3VB2iA==":"rutas-3-399x399.png","/V9JOU5ErbLW+9tJg5rAEg==":"raizarte-399x399.jpg","Gev7NovZqN8mqKd8aIzWxw==":"casa%20xue-399x399.png","8JNfqu319FcFeRScKKt03g==":"zihita-1-399x399.png","QBhXPb2kFaRsQn/I0LNgWg==":"milena-1-1080x1080.png","AZqRDw65S2pysalmmxMsoA==":"mafe-6-399x399.png","+Dnshl10CF8baCUnVN76bQ==":"img_20220320-94624-1695x2260.jpeg","hkVm9fRGvSXlcqly79tZag==":"img-20221108-wa0127-815x1087.jpg","i2JG8Gk43V5fCwKKjbHxsA==":"img-20221108-wa0127-815x1087.jpeg","H1UjwzUcjxFDbcwFcYMUEQ==":"photo-1497485692312-a26e1cc30f1d.jpeg","OezNZFPjogTiNn48PcZZXg==":"escapa-1-1080x1080.png","txFWazlDjfsGfRAM4FgSaw==":"escapa-2-1080x1080.png","DyhbDSQAHaxdU3TTvFpq/Q==":"escapa-3-1080x1080.png","G1jPQjIAtwD7qTAIDtMf3g==":"escapa-4-1080x1080.png","6ONDQSkJNy00yyXEbYJoFw==":"milena-399x399.png","1fchzpetwcB/0e92LZ4nGg==":"logo%202022%2002%20(2)-394x394.png","V2T7Pr/0dP/GHs9Xzn5dRA==":"logo%202022%2002%20(2)-394x394.png","HvcP1gi5u+13dYpS6WEBQw==":"logo%202022%2002%20(2)-394x394.png","bTEfPnFRlCMYN/Ix46+nNg==":"mafe-1080x1080.png","zt4I1nc+imwphqA9GKtMwg==":"vale-1080x1080.jpg","Vu94HA0qMG4pCbeF3OHJtw==":"vale-1080x1080.jpeg","edvtRbRtlcadoCP1zaVanQ==":"vale-394x394.jpeg","kvZFrj9ZJv9GbxsSUxjjag==":"ana-1080x1080.png","lvyQQbCJIvT67lOO4TQinQ==":"ana-1-1080x1080.png","s3YtLKzMVyGaux3QefLYhA==":"juli-787x746.jpg","MPa5qP70wAMufVC4hknigQ==":"ana-399x399.png","wj4rwFNoSlWuHF+VORk2JA==":"liz-481x380.jpg","4bpXF7jex6+YDKqiJDtqhg==":"liz-1080x1080.jpg","by0ADX3fHe5UM2BsEuAduQ==":"liz-1080x1080.jpeg","i5+ZRtMuP1qsH0as1+sbaw==":"ser%20feliz-1080x1080.jpg","10VQDVVaBlhSCIcSHdmzWA==":"ser%20feliz-1080x1080.jpeg","AY+Oaq9+437Q8y8iwrElsA==":"surreal%20artworks%20bw%20logo-1553x1649.png","7cdduf07dW0oO6mgC809yQ==":"surreal%20artworks%20color-399x424.png"}